BasicAlgo-0.0.1.dist-info/DESCRIPTION.rst
BasicAlgo-0.0.1.dist-info/METADATA
BasicAlgo-0.0.1.dist-info/RECORD
BasicAlgo-0.0.1.dist-info/WHEEL
BasicAlgo-0.0.1.dist-info/metadata.json
BasicAlgo-0.0.1.dist-info/top_level.txt
basic_algo/__init__.py
basic_algo/Dynamic Programming/CoinChange.py
basic_algo/Dynamic Programming/EggDropping.py
basic_algo/Dynamic Programming/KadanesAlgorithm.py
basic_algo/Dynamic Programming/LongestCommonSequence.py
basic_algo/Dynamic Programming/LongestCommonSubsequence.py
basic_algo/Dynamic Programming/LongestIncreasingSubsequence.py
basic_algo/Dynamic Programming/PalindromePartitioning.py
basic_algo/Dynamic Programming/SubsetSum.py
basic_algo/Dynamic Programming/WordBreak.py
basic_algo/Dynamic Programming/ZeroOneKnapsack.py
basic_algo/Dynamic Programming/__init__.py
