Metadata-Version: 2.0
Name: BasicAlgo
Version: 0.0.1
Summary: Using basic algorithms via c++
Home-page: https://github.com/kandarpkakkad/BasicAlgo
Author: Harsh Chaplot, Kandarp Kakkad
Author-email: 17bit026@nirmauni.ac.in, 17bit034@nirmauni.ac.in
License: MIT
Platform: UNKNOWN
Classifier: Programming Language :: Python :: 3
Classifier: Operating System :: OS Independent
Requires-Python: >=3.6
